rasa_chinese_plus/__init__.py
rasa_chinese_plus/info.py
rasa_chinese_plus/nlu/__init__.py
rasa_chinese_plus/nlu/tokenizers/__init__.py
rasa_chinese_plus/nlu/tokenizers/bert_tokenizer.py
rasa_chinese_plus-0.0.2.dist-info/LICENSE
rasa_chinese_plus-0.0.2.dist-info/METADATA
rasa_chinese_plus-0.0.2.dist-info/WHEEL
rasa_chinese_plus-0.0.2.dist-info/top_level.txt
rasa_chinese_plus-0.0.2.dist-info/RECORD
