Metadata-Version: 2.1
Name: rasa-chinese-plus
Version: 0.0.2
Summary: A Chinese extension package for Rasa
Home-page: https://github.com/daiyizheng/rasa-chinese-plus
Author: yizheng dai
Author-email: 387942239@qq.com
License: UNKNOWN
Platform: UNKNOWN
Classifier: Intended Audience :: Developers
Classifier: License :: OSI Approved :: Apache Software License
Classifier: Programming Language :: Python
Classifier: Programming Language :: Python :: 3.5
Classifier: Programming Language :: Python :: 3.6
Classifier: Programming Language :: Python :: 3.7
Classifier: Programming Language :: Python :: 3.8
Classifier: Topic :: Software Development
Requires-Python: >=3.5
License-File: LICENSE
